pyaig/__init__.py
pyaig/__main__.py
pyaig/aig.py
pyaig/aig_io.py
pyaig/aig_to_tt.py
pyaig/aigexpr.py
pyaig/primitives.py
pyaig/simulate.py
pyaig/truthtables.py
pyaig/utils.py
pyaig-1.0.11.data/data/requirements.txt
pyaig-1.0.11.dist-info/LICENSE.md
pyaig-1.0.11.dist-info/METADATA
pyaig-1.0.11.dist-info/WHEEL
pyaig-1.0.11.dist-info/top_level.txt
pyaig-1.0.11.dist-info/RECORD
