Metadata-Version: 2.1
Name: pyaig
Version: 1.0.11
Summary: A simple Python AIG package
Home-page: http://github.com/sterin/pyaig
Author: Baruch Sterin
Author-email: pyaig@bsterin.com
License: MIT
Platform: any
Requires-Dist: future
Requires-Dist: click
